foodx_devops_tools/VERSION
foodx_devops_tools/__init__.py
foodx_devops_tools/_declarations.py
foodx_devops_tools/_default_values.py
foodx_devops_tools/_exceptions.py
foodx_devops_tools/_log_check.py
foodx_devops_tools/_logging.py
foodx_devops_tools/_to.py
foodx_devops_tools/_version.py
foodx_devops_tools/console.py
foodx_devops_tools/deploy_me_entry.py
foodx_devops_tools/deployment.py
foodx_devops_tools/exceptions.py
foodx_devops_tools/file_maintainer_entry.py
foodx_devops_tools/patterns.py
foodx_devops_tools/profiling.py
foodx_devops_tools/puff_utility.py
foodx_devops_tools/py.typed
foodx_devops_tools/release.py
foodx_devops_tools/release_flow_entry.py
foodx_devops_tools/validate_configuration.py
foodx_devops_tools/azure/__init__.py
foodx_devops_tools/azure/cloud/__init__.py
foodx_devops_tools/azure/cloud/auth.py
foodx_devops_tools/azure/cloud/exceptions.py
foodx_devops_tools/azure/cloud/model.py
foodx_devops_tools/azure/cloud/resource.py
foodx_devops_tools/azure/cloud/resource_group.py
foodx_devops_tools/deploy_me/__init__.py
foodx_devops_tools/deploy_me/_dependency_monitor.py
foodx_devops_tools/deploy_me/_deployment.py
foodx_devops_tools/deploy_me/_exceptions.py
foodx_devops_tools/deploy_me/_main.py
foodx_devops_tools/deploy_me/_state.py
foodx_devops_tools/deploy_me/_status.py
foodx_devops_tools/deploy_me/exceptions.py
foodx_devops_tools/deploy_me/application_steps/__init__.py
foodx_devops_tools/deploy_me/application_steps/_delay.py
foodx_devops_tools/deploy_me/application_steps/_deploy.py
foodx_devops_tools/deploy_me/application_steps/_script.py
foodx_devops_tools/pipeline_config/__init__.py
foodx_devops_tools/pipeline_config/_checks.py
foodx_devops_tools/pipeline_config/_exceptions.py
foodx_devops_tools/pipeline_config/_loader.py
foodx_devops_tools/pipeline_config/_paths.py
foodx_devops_tools/pipeline_config/_structure.py
foodx_devops_tools/pipeline_config/clients.py
foodx_devops_tools/pipeline_config/deployments.py
foodx_devops_tools-0.16.0.dist-info/entry_points.txt
foodx_devops_tools-0.16.0.dist-info/LICENSE
foodx_devops_tools-0.16.0.dist-info/WHEEL
foodx_devops_tools-0.16.0.dist-info/METADATA
foodx_devops_tools-0.16.0.dist-info/RECORD
