Metadata-Version: 2.1
Name: foodx_devops_tools
Version: 0.16.0
Summary: Foodx DevOps pipeline utilities.
Home-page: https://github.com/Food-X-Technologies/foodx_devops_tools
Author: FoodX Technologies
Author-email: support@foodxtech.com
Requires-Python: >=3.8
Classifier: License :: OSI Approved :: MIT License
Requires-Dist: aiofiles >=0.7.0, <1.0
Requires-Dist: ansible >=4.4.0, <6.0
Requires-Dist: azure-devops >=6.0.0b4, <7.0
Requires-Dist: click >=8.1.2, <9
Requires-Dist: deepmerge >=1.0.1, <2
Requires-Dist: jinja2 >=3.1.1, <4
Requires-Dist: pydantic >=1.9.0, <2
Requires-Dist: ruamel.yaml >=0.17.20, <1.0
Requires-Dist: build_harness >=1.0, <2 ; extra == "dev"
Requires-Dist: pre_commit >=2.17.0, <3 ; extra == "dev"
Requires-Dist: pyjson5 >=1.5.2, <2 ; extra == "dev"
Requires-Dist: types-aiofiles >=0.1.9, <1.0 ; extra == "dev"
Requires-Dist: sphinx >=4.5.0, <5 ; extra == "doc"
Requires-Dist: sphinx_rtd_theme >=1.0, <2 ; extra == "doc"
Requires-Dist: asynctest >=0.13.0, <1.0 ; extra == "test"
Requires-Dist: pytest >=7.1.1, <8 ; extra == "test"
Requires-Dist: pytest-asyncio >=0.18.3, <1.0 ; extra == "test"
Requires-Dist: pytest-cov >=3.0, <4 ; extra == "test"
Requires-Dist: pytest-mock >=3.7.0, <4 ; extra == "test"
Provides-Extra: dev
Provides-Extra: doc
Provides-Extra: test
